{
  "docusaurus-plugin-content-docs": {
    "default": {
      "path": "/ione/docs",
      "versions": [
        {
          "name": "current",
          "label": "Next",
          "isLast": true,
          "path": "/ione/docs",
          "mainDocId": "Overview/index",
          "docs": [
            {
              "id": "Admin Settings/index",
              "path": "/ione/docs/Admin Settings/",
              "sidebar": "tutorialSidebar"
            },
            {
              "id": "Backup & View/Backup Data Management/Backup Monitoring",
              "path": "/ione/docs/Backup & View/Backup Data Management/Backup Monitoring",
              "sidebar": "tutorialSidebar"
            },
            {
              "id": "Backup & View/Backup Data Management/Delete DICOM",
              "path": "/ione/docs/Backup & View/Backup Data Management/Delete DICOM",
              "sidebar": "tutorialSidebar"
            },
            {
              "id": "Backup & View/Backup Data Management/DICOM Display Settings",
              "path": "/ione/docs/Backup & View/Backup Data Management/DICOM Display Settings",
              "sidebar": "tutorialSidebar"
            },
            {
              "id": "Backup & View/Backup Data Management/Download DICOM",
              "path": "/ione/docs/Backup & View/Backup Data Management/Download DICOM",
              "sidebar": "tutorialSidebar"
            },
            {
              "id": "Backup & View/Backup Data Management/Manage Attachments",
              "path": "/ione/docs/Backup & View/Backup Data Management/Manage Attachments",
              "sidebar": "tutorialSidebar"
            },
            {
              "id": "Backup & View/Backup Data Management/Search DICOM",
              "path": "/ione/docs/Backup & View/Backup Data Management/Search DICOM",
              "sidebar": "tutorialSidebar"
            },
            {
              "id": "Backup & View/Backup Data Management/Upload DICOM",
              "path": "/ione/docs/Backup & View/Backup Data Management/Upload DICOM",
              "sidebar": "tutorialSidebar"
            },
            {
              "id": "Backup & View/Backup Data Management/View DICOM",
              "path": "/ione/docs/Backup & View/Backup Data Management/View DICOM",
              "sidebar": "tutorialSidebar"
            },
            {
              "id": "Backup & View/Backup Setting/Backup Automation/from_autotrans_devices",
              "path": "/ione/docs/Backup & View/Backup Setting/Backup Automation/from_autotrans_devices",
              "sidebar": "tutorialSidebar"
            },
            {
              "id": "Backup & View/Backup Setting/Backup Automation/with_IRM_agent",
              "path": "/ione/docs/Backup & View/Backup Setting/Backup Automation/with_IRM_agent",
              "sidebar": "tutorialSidebar"
            },
            {
              "id": "Backup & View/Backup Setting/Create Groups",
              "path": "/ione/docs/Backup & View/Backup Setting/Create Groups",
              "sidebar": "tutorialSidebar"
            },
            {
              "id": "Backup & View/Backup Setting/Migration",
              "path": "/ione/docs/Backup & View/Backup Setting/Migration",
              "sidebar": "tutorialSidebar"
            },
            {
              "id": "Backup & View/index",
              "path": "/ione/docs/Backup & View/",
              "sidebar": "tutorialSidebar"
            },
            {
              "id": "FAQ/intro",
              "path": "/ione/docs/FAQ/intro",
              "sidebar": "tutorialSidebar"
            },
            {
              "id": "ImageWorklist/index",
              "path": "/ione/docs/ImageWorklist/",
              "sidebar": "tutorialSidebar"
            },
            {
              "id": "ImageWorklist/index",
              "path": "/ione/docs/ImageWorklist/",
              "sidebar": "tutorialSidebar"
            },
            {
              "id": "intro/intro",
              "path": "/ione/docs/intro/",
              "sidebar": "tutorialSidebar"
            },
            {
              "id": "Overview/index",
              "path": "/ione/docs/Overview/",
              "sidebar": "tutorialSidebar"
            },
            {
              "id": "Raphaview/Glossary/DICOMImport",
              "path": "/ione/docs/Raphaview/Glossary/DICOMImport",
              "sidebar": "tutorialSidebar"
            },
            {
              "id": "Raphaview/guidelines",
              "path": "/ione/docs/Raphaview/guidelines",
              "sidebar": "tutorialSidebar"
            },
            {
              "id": "Raphaview/index",
              "path": "/ione/docs/Raphaview/",
              "sidebar": "tutorialSidebar"
            },
            {
              "id": "Raphaview/Tutorials/Annotation and Measurement",
              "path": "/ione/docs/Raphaview/Tutorials/Annotation and Measurement",
              "sidebar": "tutorialSidebar"
            },
            {
              "id": "Raphaview/Tutorials/Comparing Studies",
              "path": "/ione/docs/Raphaview/Tutorials/Comparing Studies",
              "sidebar": "tutorialSidebar"
            },
            {
              "id": "Raphaview/Tutorials/DICOMExport",
              "path": "/ione/docs/Raphaview/Tutorials/DICOMExport",
              "sidebar": "tutorialSidebar"
            },
            {
              "id": "Raphaview/Tutorials/display",
              "path": "/ione/docs/Raphaview/Tutorials/display",
              "sidebar": "tutorialSidebar"
            },
            {
              "id": "Raphaview/Tutorials/ImageOrientationandManipulation",
              "path": "/ione/docs/Raphaview/Tutorials/ImageOrientationandManipulation",
              "sidebar": "tutorialSidebar"
            },
            {
              "id": "Raphaview/Tutorials/index",
              "path": "/ione/docs/Raphaview/Tutorials/",
              "sidebar": "tutorialSidebar"
            },
            {
              "id": "Raphaview/Tutorials/Overall GUI",
              "path": "/ione/docs/Raphaview/Tutorials/Overall GUI",
              "sidebar": "tutorialSidebar"
            },
            {
              "id": "Raphaview/Tutorials/Viewers_tools",
              "path": "/ione/docs/Raphaview/Tutorials/Viewers_tools",
              "sidebar": "tutorialSidebar"
            },
            {
              "id": "test_image/index",
              "path": "/ione/docs/test_image/",
              "sidebar": "tutorialSidebar"
            },
            {
              "id": "tutorial-basics/create-a-blog-post",
              "path": "/ione/docs/tutorial-basics/create-a-blog-post",
              "sidebar": "tutorialSidebar"
            },
            {
              "id": "tutorial-basics/create-a-document",
              "path": "/ione/docs/tutorial-basics/create-a-document",
              "sidebar": "tutorialSidebar"
            },
            {
              "id": "tutorial-basics/create-a-page",
              "path": "/ione/docs/tutorial-basics/create-a-page",
              "sidebar": "tutorialSidebar"
            },
            {
              "id": "tutorial-basics/deploy-your-site",
              "path": "/ione/docs/tutorial-basics/deploy-your-site",
              "sidebar": "tutorialSidebar"
            },
            {
              "id": "/category/products",
              "path": "/ione/docs/category/products",
              "sidebar": "tutorialSidebar"
            }
          ],
          "draftIds": [],
          "sidebars": {
            "tutorialSidebar": {
              "link": {
                "path": "/ione/docs/Overview/",
                "label": "Overview"
              }
            }
          }
        }
      ],
      "breadcrumbs": true
    }
  }
}